tests/__init__.py
tests/test_FIRSTClassifier.py
PyFIRSTClassifier-2.0.2.dist-info/LICENSE
PyFIRSTClassifier-2.0.2.dist-info/METADATA
PyFIRSTClassifier-2.0.2.dist-info/WHEEL
PyFIRSTClassifier-2.0.2.dist-info/entry_points.txt
PyFIRSTClassifier-2.0.2.dist-info/top_level.txt
PyFIRSTClassifier-2.0.2.dist-info/RECORD
