Metadata-Version: 2.1
Name: PyFIRSTClassifier
Version: 2.0.2
Summary: Automated morphological classification of Compact and Extended radio sources using Deep Convolutional Neural Networks
Home-page: https://github.com/wathela/FIRSTClassifier
Author: Wathela Alhassan
Author-email: wathelahamed@gmail.com
License: UNKNOWN
Platform: UNKNOWN
Classifier: Programming Language :: Python :: 3
Classifier: License :: OSI Approved :: MIT License
Classifier: Operating System :: OS Independent
License-File: LICENSE
Requires-Dist: pandas==2.0.3
Requires-Dist: numpy==1.24.3
Requires-Dist: matplotlib==3.7.5
Requires-Dist: scipy==1.10.1
Requires-Dist: astropy==5.2.2
Requires-Dist: pyvo==1.5.2
Requires-Dist: scikit-image==0.21.0
Requires-Dist: keras==2.13.1
Requires-Dist: tensorflow==2.13.1
